ivy_robot/__init__.py
ivy_robot/manipulator.py
ivy_robot/planning.py
ivy_robot/rigid_mobile.py
ivy_robot-1.1.9.dist-info/LICENCE
ivy_robot-1.1.9.dist-info/METADATA
ivy_robot-1.1.9.dist-info/WHEEL
ivy_robot-1.1.9.dist-info/top_level.txt
ivy_robot-1.1.9.dist-info/RECORD
