Metadata-Version: 2.1
Name: ivy-robot
Version: 1.1.9
Summary: Functions and classes for gradient-based robot motion planning, written in Ivy.
Home-page: https://ivy-dl.org/robot
Author: Ivy Team
Author-email: ivydl.team@gmail.com
License: Apache 2.0
Project-URL: Docs, https://ivy-dl.org/robot/
Project-URL: Source, https://github.com/ivy-dl/robot
Platform: UNKNOWN
Classifier: License :: OSI Approved :: Apache Software License
License-File: LICENCE
Requires-Dist: ivy-core
Requires-Dist: ivy-mech
